{
    "results" : [
        {
            "recipe" : {
                "ingredient": [
                    {
                        "name" : "Banana",
                        "ammount" : "1600",
                        "types" : [ "base" ]
                    },
                    {
                        "long_name" : "Amphitheatre Pkwy",
                        "short_name" : "Amphitheatre Pkwy",
                        "types" : [ "route" ]
                    },
                    {
                        "long_name" : "Mountain View",
                        "short_name" : "Mountain View",
                        "types" : [ "locality", "political" ]
                    },
                    {
                        "long_name" : "Santa Clara",
                        "short_name" : "Santa Clara",
                        "types" : [ "administrative_area_level_2", "political" ]
                    },
                    {
                        "long_name" : "California",
                        "short_name" : "CA",
                        "types" : [ "administrative_area_level_1", "political" ]
                    },
                    {
                        "long_name" : "United States",
                        "short_name" : "US",
                        "types" : [ "country", "political" ]
                    },
                    {
                        "long_name" : "94043",
                        "short_name" : "94043",
                        "types" : [ "postal_code" ]
                    }
                ]
            },
            "formatted_title" : "Best smoothie recipe ever",
            "written_by" : "ymkjp",
            "types" : [ "users_recipe" ]
        }
    ],
    "status" : "OK"
}
